README.md
setup.py
salmonella_crispr_typing/__init__.py
salmonella_crispr_typing/extract_new.py
salmonella_crispr_typing/main.py
salmonella_crispr_typing/settings.py
salmonella_crispr_typing/truncate_sequences.py
salmonella_crispr_typing/version.py
salmonella_crispr_typing.egg-info/PKG-INFO
salmonella_crispr_typing.egg-info/SOURCES.txt
salmonella_crispr_typing.egg-info/dependency_links.txt
salmonella_crispr_typing.egg-info/entry_points.txt
salmonella_crispr_typing.egg-info/requires.txt
salmonella_crispr_typing.egg-info/top_level.txt
salmonella_crispr_typing/data/spacers_Salmonella.fa
test/test_extract_new.py
test/test_main.py
test/test_truncate_sequences.py