Metadata-Version: 1.1
Name: salmonella-crispr-typing
Version: 1.0.1
Summary: This tool gets a CRISPR profile by identifying the presence of known spacers and direct repeats (DRs) in a given sequence based on a catalogue. This tool is a reimplemntation of a former Perl tool in developed by G. Guigon
Home-page: UNKNOWN
Author: Kenzo-Hugo Hillion and Laetitia Fabre
Author-email: kehillio@pasteur.fr and laetitia.fabre@pasteur.fr
License: UNKNOWN
Keywords: salmonella,crispr,fasta
Platform: UNKNOWN
Classifier: Development Status :: 5 - Production/Stable
Classifier: Topic :: Scientific/Engineering :: Bio-Informatics
Classifier: Operating System :: OS Independent
Classifier: Intended Audience :: Developers
Classifier: Intended Audience :: Science/Research
Classifier: Environment :: Console
